cli.py
anoy-0.3.1.dist-info/licenses/LICENSE.txt
modules/__init__.py
modules/dictTraversal.py
modules/errors.py
anoy-0.3.1.dist-info/METADATA
anoy-0.3.1.dist-info/WHEEL
anoy-0.3.1.dist-info/entry_points.txt
anoy-0.3.1.dist-info/top_level.txt
anoy-0.3.1.dist-info/RECORD
