Metadata-Version: 2.4
Name: anoy
Version: 0.3.1
Summary: This is a library that provides simple type checking for YAML.
Author-email: masaniki <masaniki.software@gmail.com>
License-Expression: MIT
Project-URL: Repository, https://github.com/masaniki/annotation-yaml
Project-URL: Documentation, https://github.com/masaniki/annotation-yaml/tree/master/docs
Project-URL: Issues, https://github.com/masaniki/annotation-yaml/issues
Keywords: text,YAML,CLI,type,check
Classifier: Development Status :: 1 - Planning
Classifier: Environment :: Console
Classifier: Natural Language :: Japanese
Classifier: Natural Language :: English
Classifier: Topic :: Text Processing
Requires-Python: >=3.9
License-File: LICENSE.txt
Requires-Dist: PyYAML
Dynamic: license-file
